{
   "transmitter_mode": "KYFPV",
   "mapping": [
      { "event": { "name": "STARTUP" 			}, 	"op": { "name": "SOUND",	"parm": "/mode_KYFPV.mp3" 								} },
      { "event": { "name": "CONNECTED"			},	"op": { "name": "SOUND",	"parm": "/connected.mp3"								} },
      { "event": { "name": "DISCONNECTED"		},  "op": { "name": "SOUND",	"parm": "/disconnected.mp3"								} },
      { "event": { "name": "TAKEOFF"			},	"op": { "name": "SOUND",	"parm": "/takeoff.mp3"									} },
      {	"event": { "name": "LANDING"			},	"op": { "name": "SOUND",	"parm": "/landing.mp3"									} },
      { "event": { "name": "EMERGENCY_STOP" 	},	"op": { "name": "SOUND",	"parm": "/emergency_stop.mp3"							} },
      { "event": { "name": "HEADLESS_ENABLED"	},  "op": { "name": "SOUND",	"parm": "/headless_mode_on.mp3" 						} },
      { "event": { "name": "HEADLESS_DISABLED"  },  "op": { "name": "SOUND",	"parm": "/headless_mode_off.mp3"						} },
      { "event": { "name": "GYRO_CALIBRATION"	},	"op": { "name": "SOUND",	"parm": "/gyro_calibration.mp3"							} },
      { "event": { "name": "BEEP_SHORT"			},	"op": { "name": "SOUND",	"parm": "/beep_short.mp3",			"note":"flip mode"	} },

      { "event": { "name": "ALWAYS"				},  "op": { "name": "AXIS",		"parm": "RIGHT_STICK_X",	"channel": 1	} },
      { "event": { "name": "ALWAYS"				},	"op": {	"name": "AXIS",		"parm": "RIGHT_STICK_Y",	"channel": 2	} },
      { "event": { "name": "ALWAYS"				},	"op": { "name": "AXIS",		"parm": "LEFT_STICK_Y",		"channel": 3	} },
      { "event": { "name": "ALWAYS"				},  "op": { "name": "AXIS",		"parm": "LEFT_STICK_X",		"channel": 4	} },

      { "event": { "name": "ALWAYS"				},	"op": { "name": "BUTTON",	"parm": "LEFT_BUMPER",		"channel": 5,	"note":"takeoff"		} },
      { "event": { "name": "ALWAYS"				},	"op": { "name": "BUTTON",	"parm": "RIGHT_BUMPER",		"channel": 6,	"note":"landing"		} },
      { "event": { "name": "ALWAYS"				},	"op": {	"name": "BUTTON",	"parm": "RIGHT_TRIGGER",	"channel": 7,	"note":"emergency stop"	} },
      { "event": { "name": "ALWAYS"				},	"op": {	"name": "TRIM",		"parm": "LEFT_TRIGGER",		"channel": 8,	"note":"trim modifier"	} },

      { "event": { "name": "ALWAYS"				},	"op": {	"name": "AXIS_BUTTON_LEFT",		"parm": "AXIS4",	"channel": 9,	"note":"flip mode"		} },
      { "event": { "name": "ALWAYS"				},	"op": {	"name": "AXIS_BUTTON_RIGHT",	"parm": "AXIS4",	"channel": 8,	"note":"headless mode"	} }
   ]
}